json2txttree.py
json2txttree-1.0.4.dist-info/LICENSE
json2txttree-1.0.4.dist-info/METADATA
json2txttree-1.0.4.dist-info/WHEEL
json2txttree-1.0.4.dist-info/top_level.txt
json2txttree-1.0.4.dist-info/zip-safe
json2txttree-1.0.4.dist-info/RECORD
