Metadata-Version: 2.1
Name: json2txttree
Version: 1.0.4
Summary: Library for pretty printing json data to txt files
Home-page: http://pypi.python.org/pypi/json2txttree
Author: Cibin Joseph
Author-email: cibinjoseph92@gmail.com
License: MIT
Keywords: json
Platform: UNKNOWN
Classifier: Development Status :: 5 - Production/Stable
Classifier: Intended Audience :: Science/Research
Classifier: Operating System :: OS Independent
Classifier: License :: OSI Approved :: MIT License
Classifier: Programming Language :: Python :: 3
Classifier: Topic :: Database
Requires-Python: >=3
